integradio/__init__.py
integradio/api.py
integradio/blocks.py
integradio/circuit_breaker.py
integradio/components.py
integradio/embedder.py
integradio/exceptions.py
integradio/introspect.py
integradio/logging_config.py
integradio/registry.py
integradio/specialized.py
integradio/viz.py
integradio/agent/__init__.py
integradio/agent/langchain.py
integradio/agent/mcp.py
integradio/agent/prompts.py
integradio/agent/tools.py
integradio/events/__init__.py
integradio/events/event.py
integradio/events/handlers.py
integradio/events/mesh.py
integradio/events/security.py
integradio/events/websocket.py
integradio/inspector/__init__.py
integradio/inspector/core.py
integradio/inspector/dataflow.py
integradio/inspector/panel.py
integradio/inspector/search.py
integradio/inspector/tree.py
integradio/pages/__init__.py
integradio/pages/analytics.py
integradio/pages/chat.py
integradio/pages/dashboard.py
integradio/pages/datatable.py
integradio/pages/form.py
integradio/pages/gallery.py
integradio/pages/help.py
integradio/pages/hero.py
integradio/pages/settings.py
integradio/pages/upload.py
integradio/visual/__init__.py
integradio/visual/bridge.py
integradio/visual/diff.py
integradio/visual/export.py
integradio/visual/figma.py
integradio/visual/library.py
integradio/visual/screenshot.py
integradio/visual/spec.py
integradio/visual/theme.py
integradio/visual/tokens.py
integradio/visual/validation.py
integradio/visual/viewer.py
integradio-0.3.0.dist-info/licenses/LICENSE
integradio-0.3.0.dist-info/METADATA
integradio-0.3.0.dist-info/WHEEL
integradio-0.3.0.dist-info/top_level.txt
integradio-0.3.0.dist-info/RECORD
