Metadata-Version: 2.4
Name: integradio
Version: 0.3.0
Summary: Vector-embedded Gradio components for semantic codebase navigation
Author: AI Development Lab
Maintainer: AI Development Lab
License-Expression: MIT
Project-URL: Homepage, https://github.com/mikeyfrilot/integradio
Project-URL: Documentation, https://github.com/mikeyfrilot/integradio#readme
Project-URL: Repository, https://github.com/mikeyfrilot/integradio
Project-URL: Issues, https://github.com/mikeyfrilot/integradio/issues
Keywords: gradio,embeddings,semantic-search,ui-components,vector-database,visualization,ollama,nomic-embed-text
Classifier: Development Status :: 3 - Alpha
Classifier: Intended Audience :: Developers
Classifier: Programming Language :: Python :: 3
Classifier: Programming Language :: Python :: 3.10
Classifier: Programming Language :: Python :: 3.11
Classifier: Programming Language :: Python :: 3.12
Classifier: Programming Language :: Python :: 3.13
Classifier: Topic :: Software Development :: User Interfaces
Classifier: Topic :: Scientific/Engineering :: Artificial Intelligence
Classifier: Typing :: Typed
Requires-Python: >=3.10
License-File: LICENSE
Requires-Dist: gradio<7.0.0,>=4.0.0
Requires-Dist: numpy>=1.24.0
Requires-Dist: httpx>=0.24.0
Requires-Dist: pandas>=2.0.0
Provides-Extra: hnsw
Requires-Dist: hnswlib>=0.7.0; extra == "hnsw"
Provides-Extra: api
Requires-Dist: fastapi>=0.100.0; extra == "api"
Requires-Dist: uvicorn>=0.23.0; extra == "api"
Provides-Extra: pages
Requires-Dist: pandas>=2.0.0; extra == "pages"
Provides-Extra: all
Requires-Dist: hnswlib>=0.7.0; extra == "all"
Requires-Dist: fastapi>=0.100.0; extra == "all"
Requires-Dist: uvicorn>=0.23.0; extra == "all"
Requires-Dist: pandas>=2.0.0; extra == "all"
Provides-Extra: dev
Requires-Dist: pytest>=8.0.0; extra == "dev"
Requires-Dist: pytest-asyncio>=0.23.0; extra == "dev"
Requires-Dist: pytest-cov>=4.1.0; extra == "dev"
Requires-Dist: ruff>=0.4.0; extra == "dev"
Requires-Dist: mypy>=1.10.0; extra == "dev"
Dynamic: license-file
